neurite/__init__.py
neurite/py/__init__.py
neurite/py/data.py
neurite/py/dataproc.py
neurite/py/plot.py
neurite/py/utils.py
neurite/tf/__init__.py
neurite/tf/callbacks.py
neurite/tf/data.py
neurite/tf/generators.py
neurite/tf/layers.py
neurite/tf/losses.py
neurite/tf/metrics.py
neurite/tf/modelio.py
neurite/tf/models.py
neurite/tf/regularizers.py
neurite/tf/utils/__init__.py
neurite/tf/utils/augment.py
neurite/tf/utils/model.py
neurite/tf/utils/seg.py
neurite/tf/utils/utils.py
neurite/tf/utils/vae.py
neuron/__init__.py
neurite-0.2.dist-info/LICENSE.md
neurite-0.2.dist-info/METADATA
neurite-0.2.dist-info/WHEEL
neurite-0.2.dist-info/top_level.txt
neurite-0.2.dist-info/RECORD
